translator_module/__init__.py
translator_module/cli.py
translator_module/comment_extractor.py
translator_module/file_handler.py
translator_module/gui.py
translator_module/translator.py
translator_module/utils.py
pydoc_translate-1.0.2.dist-info/METADATA
pydoc_translate-1.0.2.dist-info/WHEEL
pydoc_translate-1.0.2.dist-info/entry_points.txt
pydoc_translate-1.0.2.dist-info/top_level.txt
pydoc_translate-1.0.2.dist-info/RECORD
