Metadata-Version: 2.1
Name: pydoc-translate
Version: 1.0.2
Summary: Translate Python comments and docstrings into any language.
Home-page: https://github.com/Taks-69/PyDoc-Translate
Author: Taks-69
Author-email: taks.help69@gmail.com
License: UNKNOWN
Platform: UNKNOWN
Classifier: Programming Language :: Python :: 3
Classifier: License :: OSI Approved :: GNU General Public License v3 (GPLv3)
Classifier: Operating System :: OS Independent
Requires-Python: >=3.6
Requires-Dist: googletrans ==4.0.0-rc1
